cts/__init__.py
cts/input/__init__.py
cts/input/input_values.py
cts/output/__init__.py
cts/output/output_values.py
ersmoreira/__init__.py
ersmoreira/getvalues.py
ersmoreira/greeting.py
EdgarFirstPIP-0.0.1.5.dist-info/METADATA
EdgarFirstPIP-0.0.1.5.dist-info/WHEEL
EdgarFirstPIP-0.0.1.5.dist-info/top_level.txt
EdgarFirstPIP-0.0.1.5.dist-info/RECORD
